[
    {
        "x": -5,
        "y": 0,
        "z": 1,
        "color": "#cf0000"
    },
    {
        "x": -5,
        "y": 0,
        "z": 2,
        "color": "#c20000"
    },
    {
        "x": -5,
        "y": 0,
        "z": 3,
        "color": "#d20000"
    },
    {
        "x": -4,
        "y": 0,
        "z": 0,
        "color": "#d60000"
    },
    {
        "x": -4,
        "y": 0,
        "z": 1,
        "color": "#c20000"
    },
    {
        "x": -4,
        "y": 0,
        "z": 2,
        "color": "#c80000"
    },
    {
        "x": -4,
        "y": 0,
        "z": 3,
        "color": "#cd0000"
    },
    {
        "x": -3,
        "y": 0,
        "z": 1,
        "color": "#d40000"
    },
    {
        "x": -3,
        "y": 0,
        "z": 2,
        "color": "#c80000"
    },
    {
        "x": -5,
        "y": 1,
        "z": 1,
        "color": "#d70000"
    },
    {
        "x": -5,
        "y": 1,
        "z": 2,
        "color": "#fefefe"
    },
    {
        "x": -5,
        "y": 1,
        "z": 3,
        "color": "#d50000"
    },
    {
        "x": -4,
        "y": 1,
        "z": 0,
        "color": "#d70000"
    },
    {
        "x": -4,
        "y": 1,
        "z": 1,
        "color": "#d40000"
    },
    {
        "x": -4,
        "y": 1,
        "z": 2,
        "color": "#fcfcfc"
    },
    {
        "x": -4,
        "y": 1,
        "z": 3,
        "color": "#d30000"
    },
    {
        "x": -3,
        "y": 1,
        "z": 1,
        "color": "#d50000"
    },
    {
        "x": -3,
        "y": 1,
        "z": 2,
        "color": "#ffffff"
    },
    {
        "x": -4,
        "y": 2,
        "z": 1,
        "color": "#ca0000"
    },
    {
        "x": -4,
        "y": 2,
        "z": 2,
        "color": "#d30000"
    },
    {
        "x": -3,
        "y": 2,
        "z": 1,
        "color": "#c60000"
    },
    {
        "x": -3,
        "y": 2,
        "z": 2,
        "color": "#d50000"
    },
    {
        "x": 5,
        "y": 0,
        "z": 1,
        "color": "#d40000"
    },
    {
        "x": 5,
        "y": 0,
        "z": 2,
        "color": "#c10000"
    },
    {
        "x": 5,
        "y": 0,
        "z": 3,
        "color": "#c00000"
    },
    {
        "x": 4,
        "y": 0,
        "z": 0,
        "color": "#cc0000"
    },
    {
        "x": 4,
        "y": 0,
        "z": 1,
        "color": "#c40000"
    },
    {
        "x": 4,
        "y": 0,
        "z": 2,
        "color": "#d60000"
    },
    {
        "x": 4,
        "y": 0,
        "z": 3,
        "color": "#c90000"
    },
    {
        "x": 3,
        "y": 0,
        "z": 1,
        "color": "#c20000"
    },
    {
        "x": 3,
        "y": 0,
        "z": 2,
        "color": "#ce0000"
    },
    {
        "x": 5,
        "y": 1,
        "z": 1,
        "color": "#c10000"
    },
    {
        "x": 5,
        "y": 1,
        "z": 2,
        "color": "#ffffff"
    },
    {
        "x": 5,
        "y": 1,
        "z": 3,
        "color": "#c40000"
    },
    {
        "x": 4,
        "y": 1,
        "z": 0,
        "color": "#d40000"
    },
    {
        "x": 4,
        "y": 1,
        "z": 1,
        "color": "#d70000"
    },
    {
        "x": 4,
        "y": 1,
        "z": 2,
        "color": "#fefefe"
    },
    {
        "x": 4,
        "y": 1,
        "z": 3,
        "color": "#c00000"
    },
    {
        "x": 3,
        "y": 1,
        "z": 1,
        "color": "#c40000"
    },
    {
        "x": 3,
        "y": 1,
        "z": 2,
        "color": "#fdfdfd"
    },
    {
        "x": 4,
        "y": 2,
        "z": 1,
        "color": "#cb0000"
    },
    {
        "x": 4,
        "y": 2,
        "z": 2,
        "color": "#c60000"
    },
    {
        "x": 3,
        "y": 2,
        "z": 1,
        "color": "#cb0000"
    },
    {
        "x": 3,
        "y": 2,
        "z": 2,
        "color": "#d20000"
    },
    {
        "x": -4,
        "y": 3,
        "z": 2,
        "color": "#1f52bc"
    },
    {
        "x": -4,
        "y": 4,
        "z": 2,
        "color": "#2054c1"
    },
    {
        "x": -4,
        "y": 5,
        "z": 2,
        "color": "#1d4eb3"
    },
    {
        "x": -4,
        "y": 6,
        "z": 2,
        "color": "#1f52bd"
    },
    {
        "x": -3,
        "y": 7,
        "z": 2,
        "color": "#1d4eb4"
    },
    {
        "x": -2,
        "y": 7,
        "z": 2,
        "color": "#1f52bd"
    },
    {
        "x": 4,
        "y": 3,
        "z": 2,
        "color": "#1e50b7"
    },
    {
        "x": 4,
        "y": 4,
        "z": 2,
        "color": "#1c4bad"
    },
    {
        "x": 4,
        "y": 5,
        "z": 2,
        "color": "#1f53bf"
    },
    {
        "x": 4,
        "y": 6,
        "z": 2,
        "color": "#1b4bad"
    },
    {
        "x": 3,
        "y": 7,
        "z": 2,
        "color": "#2156c5"
    },
    {
        "x": 2,
        "y": 7,
        "z": 2,
        "color": "#1b4bac"
    },
    {
        "x": -2,
        "y": 8,
        "z": 1,
        "color": "#1c4caf"
    },
    {
        "x": -2,
        "y": 8,
        "z": 2,
        "color": "#2055c2"
    },
    {
        "x": -2,
        "y": 8,
        "z": 3,
        "color": "#1b49aa"
    },
    {
        "x": -1,
        "y": 8,
        "z": 0,
        "color": "#1b4aac"
    },
    {
        "x": -1,
        "y": 8,
        "z": 1,
        "color": "#1e50b7"
    },
    {
        "x": -1,
        "y": 8,
        "z": 2,
        "color": "#1e50b8"
    },
    {
        "x": -1,
        "y": 8,
        "z": 3,
        "color": "#2054c1"
    },
    {
        "x": 0,
        "y": 8,
        "z": 0,
        "color": "#1e4fb7"
    },
    {
        "x": 0,
        "y": 8,
        "z": 1,
        "color": "#1c4db1"
    },
    {
        "x": 0,
        "y": 8,
        "z": 2,
        "color": "#1f52bd"
    },
    {
        "x": 0,
        "y": 8,
        "z": 3,
        "color": "#1e50b9"
    },
    {
        "x": 1,
        "y": 8,
        "z": 0,
        "color": "#1d4fb5"
    },
    {
        "x": 1,
        "y": 8,
        "z": 1,
        "color": "#1f53be"
    },
    {
        "x": 1,
        "y": 8,
        "z": 2,
        "color": "#2054c0"
    },
    {
        "x": 1,
        "y": 8,
        "z": 3,
        "color": "#1f52bd"
    },
    {
        "x": 2,
        "y": 8,
        "z": 1,
        "color": "#2053bf"
    },
    {
        "x": 2,
        "y": 8,
        "z": 2,
        "color": "#1e51ba"
    },
    {
        "x": 2,
        "y": 8,
        "z": 3,
        "color": "#1f51bb"
    },
    {
        "x": -2,
        "y": 9,
        "z": 1,
        "color": "#2054c0"
    },
    {
        "x": -2,
        "y": 9,
        "z": 2,
        "color": "#f5d3c8"
    },
    {
        "x": -2,
        "y": 9,
        "z": 3,
        "color": "#1c4bae"
    },
    {
        "x": -1,
        "y": 9,
        "z": 0,
        "color": "#2156c4"
    },
    {
        "x": -1,
        "y": 9,
        "z": 1,
        "color": "#2054c0"
    },
    {
        "x": -1,
        "y": 9,
        "z": 2,
        "color": "#f5d0c6"
    },
    {
        "x": -1,
        "y": 9,
        "z": 3,
        "color": "#1f53bd"
    },
    {
        "x": 0,
        "y": 9,
        "z": 0,
        "color": "#1b4aac"
    },
    {
        "x": 0,
        "y": 9,
        "z": 1,
        "color": "#f4cabd"
    },
    {
        "x": 0,
        "y": 9,
        "z": 2,
        "color": "#f5d1c6"
    },
    {
        "x": 0,
        "y": 9,
        "z": 3,
        "color": "#1e50b7"
    },
    {
        "x": 1,
        "y": 9,
        "z": 0,
        "color": "#1b4aab"
    },
    {
        "x": 1,
        "y": 9,
        "z": 1,
        "color": "#1b4aac"
    },
    {
        "x": 1,
        "y": 9,
        "z": 2,
        "color": "#f5cec3"
    },
    {
        "x": 1,
        "y": 9,
        "z": 3,
        "color": "#2054c0"
    },
    {
        "x": 2,
        "y": 9,
        "z": 1,
        "color": "#1e4fb6"
    },
    {
        "x": 2,
        "y": 9,
        "z": 2,
        "color": "#f5d2c8"
    },
    {
        "x": 2,
        "y": 9,
        "z": 3,
        "color": "#1f52bd"
    },
    {
        "x": -2,
        "y": 10,
        "z": 1,
        "color": "#1c4bae"
    },
    {
        "x": -2,
        "y": 10,
        "z": 2,
        "color": "#f6d3c9"
    },
    {
        "x": -2,
        "y": 10,
        "z": 3,
        "color": "#2054c0"
    },
    {
        "x": -1,
        "y": 10,
        "z": 0,
        "color": "#2155c4"
    },
    {
        "x": -1,
        "y": 10,
        "z": 1,
        "color": "#2156c4"
    },
    {
        "x": -1,
        "y": 10,
        "z": 2,
        "color": "#f4cabd"
    },
    {
        "x": -1,
        "y": 10,
        "z": 3,
        "color": "#1c4caf"
    },
    {
        "x": 0,
        "y": 10,
        "z": 0,
        "color": "#1f53bf"
    },
    {
        "x": 0,
        "y": 10,
        "z": 1,
        "color": "#f5cfc3"
    },
    {
        "x": 0,
        "y": 10,
        "z": 2,
        "color": "#f5cec2"
    },
    {
        "x": 0,
        "y": 10,
        "z": 3,
        "color": "#1e51b9"
    },
    {
        "x": 1,
        "y": 10,
        "z": 0,
        "color": "#1e51b9"
    },
    {
        "x": 1,
        "y": 10,
        "z": 1,
        "color": "#1d4db2"
    },
    {
        "x": 1,
        "y": 10,
        "z": 2,
        "color": "#f4cbbf"
    },
    {
        "x": 1,
        "y": 10,
        "z": 3,
        "color": "#1c4cb0"
    },
    {
        "x": 2,
        "y": 10,
        "z": 1,
        "color": "#1c4caf"
    },
    {
        "x": 2,
        "y": 10,
        "z": 2,
        "color": "#f4cdc1"
    },
    {
        "x": 2,
        "y": 10,
        "z": 3,
        "color": "#2156c4"
    },
    {
        "x": -2,
        "y": 11,
        "z": 1,
        "color": "#1d4db2"
    },
    {
        "x": -2,
        "y": 11,
        "z": 2,
        "color": "#f4cbbf"
    },
    {
        "x": -2,
        "y": 11,
        "z": 3,
        "color": "#1e50b7"
    },
    {
        "x": -1,
        "y": 11,
        "z": 1,
        "color": "#1d4eb3"
    },
    {
        "x": -1,
        "y": 11,
        "z": 2,
        "color": "#f6d6cd"
    },
    {
        "x": -1,
        "y": 11,
        "z": 3,
        "color": "#2054c0"
    },
    {
        "x": 0,
        "y": 11,
        "z": 1,
        "color": "#f4c8bb"
    },
    {
        "x": 0,
        "y": 11,
        "z": 2,
        "color": "#f6d6cc"
    },
    {
        "x": 0,
        "y": 11,
        "z": 3,
        "color": "#1e50b8"
    },
    {
        "x": 1,
        "y": 11,
        "z": 1,
        "color": "#1c4caf"
    },
    {
        "x": 1,
        "y": 11,
        "z": 2,
        "color": "#f4cabd"
    },
    {
        "x": 1,
        "y": 11,
        "z": 3,
        "color": "#1b4aab"
    },
    {
        "x": 2,
        "y": 11,
        "z": 1,
        "color": "#1c4bad"
    },
    {
        "x": 2,
        "y": 11,
        "z": 2,
        "color": "#f6d5cb"
    },
    {
        "x": 2,
        "y": 11,
        "z": 3,
        "color": "#2055c2"
    },
    {
        "x": -2,
        "y": 12,
        "z": 1,
        "color": "#1d4eb5"
    },
    {
        "x": -2,
        "y": 12,
        "z": 2,
        "color": "#1c4bae"
    },
    {
        "x": -2,
        "y": 12,
        "z": 3,
        "color": "#1b49aa"
    },
    {
        "x": -1,
        "y": 12,
        "z": 1,
        "color": "#2055c3"
    },
    {
        "x": -1,
        "y": 12,
        "z": 2,
        "color": "#2055c2"
    },
    {
        "x": -1,
        "y": 12,
        "z": 3,
        "color": "#1c4caf"
    },
    {
        "x": 0,
        "y": 12,
        "z": 1,
        "color": "#1d4eb4"
    },
    {
        "x": 0,
        "y": 12,
        "z": 2,
        "color": "#2156c4"
    },
    {
        "x": 0,
        "y": 12,
        "z": 3,
        "color": "#1f51ba"
    },
    {
        "x": 1,
        "y": 12,
        "z": 1,
        "color": "#1c4caf"
    },
    {
        "x": 1,
        "y": 12,
        "z": 2,
        "color": "#1f52bc"
    },
    {
        "x": 1,
        "y": 12,
        "z": 3,
        "color": "#1f52bc"
    },
    {
        "x": 2,
        "y": 12,
        "z": 1,
        "color": "#1d4eb3"
    },
    {
        "x": 2,
        "y": 12,
        "z": 2,
        "color": "#1d4eb4"
    },
    {
        "x": 2,
        "y": 12,
        "z": 3,
        "color": "#2054c1"
    },
    {
        "x": -1,
        "y": 13,
        "z": 1,
        "color": "#1f52bd"
    },
    {
        "x": -1,
        "y": 13,
        "z": 2,
        "color": "#2055c3"
    },
    {
        "x": 0,
        "y": 13,
        "z": 1,
        "color": "#2054c1"
    },
    {
        "x": 0,
        "y": 13,
        "z": 2,
        "color": "#1f53be"
    },
    {
        "x": 1,
        "y": 13,
        "z": 1,
        "color": "#2054c0"
    },
    {
        "x": 1,
        "y": 13,
        "z": 2,
        "color": "#1e50b8"
    },
    {
        "x": -3,
        "y": 9,
        "z": 2,
        "color": "#f5cec2"
    },
    {
        "x": -4,
        "y": 9,
        "z": 2,
        "color": "#f6d5cb"
    },
    {
        "x": -5,
        "y": 9,
        "z": 2,
        "color": "#f4cbbf"
    },
    {
        "x": -5,
        "y": 10,
        "z": 2,
        "color": "#ffffff"
    },
    {
        "x": -6,
        "y": 10,
        "z": 2,
        "color": "#ffffff"
    },
    {
        "x": -5,
        "y": 10,
        "z": 1,
        "color": "#fcfcfc"
    },
    {
        "x": -5,
        "y": 10,
        "z": 3,
        "color": "#fdfdfd"
    },
    {
        "x": -6,
        "y": 9,
        "z": 2,
        "color": "#ffffff"
    },
    {
        "x": -6,
        "y": 11,
        "z": 2,
        "color": "#ffffff"
    },
    {
        "x": 3,
        "y": 9,
        "z": 2,
        "color": "#f6d3c8"
    },
    {
        "x": 4,
        "y": 9,
        "z": 2,
        "color": "#f6d6cd"
    },
    {
        "x": 5,
        "y": 9,
        "z": 2,
        "color": "#f6d7ce"
    },
    {
        "x": 5,
        "y": 10,
        "z": 2,
        "color": "#fbfbfb"
    },
    {
        "x": 6,
        "y": 10,
        "z": 2,
        "color": "#fefefe"
    },
    {
        "x": 5,
        "y": 10,
        "z": 1,
        "color": "#fefefe"
    },
    {
        "x": 5,
        "y": 10,
        "z": 3,
        "color": "#ffffff"
    },
    {
        "x": 6,
        "y": 9,
        "z": 2,
        "color": "#ffffff"
    },
    {
        "x": 6,
        "y": 11,
        "z": 2,
        "color": "#ffffff"
    },
    {
        "x": -2,
        "y": 14,
        "z": 0,
        "color": "#2055c3"
    },
    {
        "x": -2,
        "y": 14,
        "z": 1,
        "color": "#1f52bd"
    },
    {
        "x": -2,
        "y": 14,
        "z": 2,
        "color": "#1c4db1"
    },
    {
        "x": -2,
        "y": 14,
        "z": 3,
        "color": "#1c4caf"
    },
    {
        "x": -1,
        "y": 14,
        "z": -1,
        "color": "#1b4aaa"
    },
    {
        "x": -1,
        "y": 14,
        "z": 0,
        "color": "#1e4fb6"
    },
    {
        "x": -1,
        "y": 14,
        "z": 1,
        "color": "#1d4fb5"
    },
    {
        "x": -1,
        "y": 14,
        "z": 2,
        "color": "#1f52bc"
    },
    {
        "x": -1,
        "y": 14,
        "z": 3,
        "color": "#2054c1"
    },
    {
        "x": 0,
        "y": 14,
        "z": -1,
        "color": "#1f53bf"
    },
    {
        "x": 0,
        "y": 14,
        "z": 0,
        "color": "#2054c0"
    },
    {
        "x": 0,
        "y": 14,
        "z": 1,
        "color": "#1c4caf"
    },
    {
        "x": 0,
        "y": 14,
        "z": 2,
        "color": "#1b4aab"
    },
    {
        "x": 0,
        "y": 14,
        "z": 3,
        "color": "#1c4caf"
    },
    {
        "x": 1,
        "y": 14,
        "z": -1,
        "color": "#1d4db2"
    },
    {
        "x": 1,
        "y": 14,
        "z": 0,
        "color": "#2055c2"
    },
    {
        "x": 1,
        "y": 14,
        "z": 1,
        "color": "#2054c1"
    },
    {
        "x": 1,
        "y": 14,
        "z": 2,
        "color": "#1b4aab"
    },
    {
        "x": 1,
        "y": 14,
        "z": 3,
        "color": "#1e50b9"
    },
    {
        "x": 2,
        "y": 14,
        "z": 0,
        "color": "#1d4eb4"
    },
    {
        "x": 2,
        "y": 14,
        "z": 1,
        "color": "#1c4bad"
    },
    {
        "x": 2,
        "y": 14,
        "z": 2,
        "color": "#1b4bad"
    },
    {
        "x": 2,
        "y": 14,
        "z": 3,
        "color": "#1f52bc"
    },
    {
        "x": -3,
        "y": 15,
        "z": 0,
        "color": "#1d4fb5"
    },
    {
        "x": -3,
        "y": 15,
        "z": 1,
        "color": "#1c4bae"
    },
    {
        "x": -3,
        "y": 15,
        "z": 2,
        "color": "#1e51ba"
    },
    {
        "x": -2,
        "y": 15,
        "z": -1,
        "color": "#1c4caf"
    },
    {
        "x": -2,
        "y": 15,
        "z": 0,
        "color": "#1c4db1"
    },
    {
        "x": -2,
        "y": 15,
        "z": 1,
        "color": "#f6d5cb"
    },
    {
        "x": -2,
        "y": 15,
        "z": 2,
        "color": "#f5d0c5"
    },
    {
        "x": -2,
        "y": 15,
        "z": 3,
        "color": "#1e50b8"
    },
    {
        "x": -1,
        "y": 15,
        "z": -1,
        "color": "#1d4db1"
    },
    {
        "x": -1,
        "y": 15,
        "z": 0,
        "color": "#f6d8cf"
    },
    {
        "x": -1,
        "y": 15,
        "z": 1,
        "color": "#f4c9bb"
    },
    {
        "x": -1,
        "y": 15,
        "z": 2,
        "color": "#f5d1c6"
    },
    {
        "x": -1,
        "y": 15,
        "z": 3,
        "color": "#1d4eb3"
    },
    {
        "x": 0,
        "y": 15,
        "z": -1,
        "color": "#1b4aab"
    },
    {
        "x": 0,
        "y": 15,
        "z": 0,
        "color": "#f4ccbf"
    },
    {
        "x": 0,
        "y": 15,
        "z": 1,
        "color": "#f6d7ce"
    },
    {
        "x": 0,
        "y": 15,
        "z": 2,
        "color": "#f4ccc0"
    },
    {
        "x": 0,
        "y": 15,
        "z": 3,
        "color": "#1f51ba"
    },
    {
        "x": 1,
        "y": 15,
        "z": -1,
        "color": "#1b49aa"
    },
    {
        "x": 1,
        "y": 15,
        "z": 0,
        "color": "#f5d2c8"
    },
    {
        "x": 1,
        "y": 15,
        "z": 1,
        "color": "#f4c9bc"
    },
    {
        "x": 1,
        "y": 15,
        "z": 2,
        "color": "#f5d2c8"
    },
    {
        "x": 1,
        "y": 15,
        "z": 3,
        "color": "#2054c0"
    },
    {
        "x": 2,
        "y": 15,
        "z": -1,
        "color": "#1f51bb"
    },
    {
        "x": 2,
        "y": 15,
        "z": 0,
        "color": "#1c4cb0"
    },
    {
        "x": 2,
        "y": 15,
        "z": 1,
        "color": "#f5d0c4"
    },
    {
        "x": 2,
        "y": 15,
        "z": 2,
        "color": "#f4cbbe"
    },
    {
        "x": 2,
        "y": 15,
        "z": 3,
        "color": "#1c4caf"
    },
    {
        "x": 3,
        "y": 15,
        "z": 0,
        "color": "#1c4cb0"
    },
    {
        "x": 3,
        "y": 15,
        "z": 1,
        "color": "#1c4db1"
    },
    {
        "x": 3,
        "y": 15,
        "z": 2,
        "color": "#1c4cb0"
    },
    {
        "x": -3,
        "y": 16,
        "z": 0,
        "color": "#1c4bae"
    },
    {
        "x": -3,
        "y": 16,
        "z": 1,
        "color": "#2054c0"
    },
    {
        "x": -2,
        "y": 16,
        "z": -1,
        "color": "#1e50b8"
    },
    {
        "x": -2,
        "y": 16,
        "z": 0,
        "color": "#f5d1c6"
    },
    {
        "x": -2,
        "y": 16,
        "z": 1,
        "color": "#ffffff"
    },
    {
        "x": -2,
        "y": 16,
        "z": 2,
        "color": "#f5d0c5"
    },
    {
        "x": -2,
        "y": 16,
        "z": 3,
        "color": "#1d4eb5"
    },
    {
        "x": -1,
        "y": 16,
        "z": -1,
        "color": "#2055c2"
    },
    {
        "x": -1,
        "y": 16,
        "z": 0,
        "color": "#f6d7ce"
    },
    {
        "x": -1,
        "y": 16,
        "z": 1,
        "color": "#ffffff"
    },
    {
        "x": -1,
        "y": 16,
        "z": 2,
        "color": "#f5d1c6"
    },
    {
        "x": -1,
        "y": 16,
        "z": 3,
        "color": "#1d4eb5"
    },
    {
        "x": 0,
        "y": 16,
        "z": -1,
        "color": "#1d4fb5"
    },
    {
        "x": 0,
        "y": 16,
        "z": 0,
        "color": "#f6d4ca"
    },
    {
        "x": 0,
        "y": 16,
        "z": 1,
        "color": "#f4cdc1"
    },
    {
        "x": 0,
        "y": 16,
        "z": 2,
        "color": "#f5d3c8"
    },
    {
        "x": 0,
        "y": 16,
        "z": 3,
        "color": "#1c4caf"
    },
    {
        "x": 1,
        "y": 16,
        "z": -1,
        "color": "#1d4eb4"
    },
    {
        "x": 1,
        "y": 16,
        "z": 0,
        "color": "#f5d0c5"
    },
    {
        "x": 1,
        "y": 16,
        "z": 1,
        "color": "#ffffff"
    },
    {
        "x": 1,
        "y": 16,
        "z": 2,
        "color": "#f6d7ce"
    },
    {
        "x": 1,
        "y": 16,
        "z": 3,
        "color": "#1d4eb3"
    },
    {
        "x": 2,
        "y": 16,
        "z": -1,
        "color": "#1d4eb4"
    },
    {
        "x": 2,
        "y": 16,
        "z": 0,
        "color": "#f6d7cd"
    },
    {
        "x": 2,
        "y": 16,
        "z": 1,
        "color": "#ffffff"
    },
    {
        "x": 2,
        "y": 16,
        "z": 2,
        "color": "#f4cabd"
    },
    {
        "x": 2,
        "y": 16,
        "z": 3,
        "color": "#2156c4"
    },
    {
        "x": 3,
        "y": 16,
        "z": 0,
        "color": "#1e51b9"
    },
    {
        "x": 3,
        "y": 16,
        "z": 1,
        "color": "#1f51ba"
    },
    {
        "x": -3,
        "y": 17,
        "z": 0,
        "color": "#1f51bb"
    },
    {
        "x": -3,
        "y": 17,
        "z": 1,
        "color": "#1e4fb6"
    },
    {
        "x": -2,
        "y": 17,
        "z": -1,
        "color": "#1c4bae"
    },
    {
        "x": -2,
        "y": 17,
        "z": 0,
        "color": "#010101"
    },
    {
        "x": -2,
        "y": 17,
        "z": 1,
        "color": "#1fa446"
    },
    {
        "x": -2,
        "y": 17,
        "z": 2,
        "color": "#f5cfc3"
    },
    {
        "x": -2,
        "y": 17,
        "z": 3,
        "color": "#2055c2"
    },
    {
        "x": -1,
        "y": 17,
        "z": -1,
        "color": "#1c4bad"
    },
    {
        "x": -1,
        "y": 17,
        "z": 0,
        "color": "#f6d5cc"
    },
    {
        "x": -1,
        "y": 17,
        "z": 1,
        "color": "#25be52"
    },
    {
        "x": -1,
        "y": 17,
        "z": 2,
        "color": "#f6d4ca"
    },
    {
        "x": -1,
        "y": 17,
        "z": 3,
        "color": "#1d4db3"
    },
    {
        "x": 0,
        "y": 17,
        "z": -1,
        "color": "#2156c5"
    },
    {
        "x": 0,
        "y": 17,
        "z": 0,
        "color": "#f6d4cb"
    },
    {
        "x": 0,
        "y": 17,
        "z": 1,
        "color": "#f4ccbf"
    },
    {
        "x": 0,
        "y": 17,
        "z": 2,
        "color": "#f5cfc4"
    },
    {
        "x": 0,
        "y": 17,
        "z": 3,
        "color": "#2055c2"
    },
    {
        "x": 1,
        "y": 17,
        "z": -1,
        "color": "#1e50b9"
    },
    {
        "x": 1,
        "y": 17,
        "z": 0,
        "color": "#f5cec3"
    },
    {
        "x": 1,
        "y": 17,
        "z": 1,
        "color": "#1fa446"
    },
    {
        "x": 1,
        "y": 17,
        "z": 2,
        "color": "#f5d2c7"
    },
    {
        "x": 1,
        "y": 17,
        "z": 3,
        "color": "#1d4db2"
    },
    {
        "x": 2,
        "y": 17,
        "z": -1,
        "color": "#1f52bd"
    },
    {
        "x": 2,
        "y": 17,
        "z": 0,
        "color": "#343434"
    },
    {
        "x": 2,
        "y": 17,
        "z": 1,
        "color": "#1fa346"
    },
    {
        "x": 2,
        "y": 17,
        "z": 2,
        "color": "#f6d6cd"
    },
    {
        "x": 2,
        "y": 17,
        "z": 3,
        "color": "#2055c3"
    },
    {
        "x": 3,
        "y": 17,
        "z": 0,
        "color": "#1e4fb6"
    },
    {
        "x": 3,
        "y": 17,
        "z": 1,
        "color": "#1f52bd"
    },
    {
        "x": -3,
        "y": 18,
        "z": 0,
        "color": "#1e51b9"
    },
    {
        "x": -2,
        "y": 18,
        "z": -1,
        "color": "#2055c2"
    },
    {
        "x": -2,
        "y": 18,
        "z": 0,
        "color": "#f5d0c5"
    },
    {
        "x": -2,
        "y": 18,
        "z": 1,
        "color": "#f6d7ce"
    },
    {
        "x": -2,
        "y": 18,
        "z": 2,
        "color": "#1d4eb3"
    },
    {
        "x": -1,
        "y": 18,
        "z": -1,
        "color": "#1c4bae"
    },
    {
        "x": -1,
        "y": 18,
        "z": 0,
        "color": "#f4c9bc"
    },
    {
        "x": -1,
        "y": 18,
        "z": 1,
        "color": "#f6d6cd"
    },
    {
        "x": -1,
        "y": 18,
        "z": 2,
        "color": "#1b4aac"
    },
    {
        "x": 0,
        "y": 18,
        "z": -1,
        "color": "#1c4bae"
    },
    {
        "x": 0,
        "y": 18,
        "z": 0,
        "color": "#f6d5cc"
    },
    {
        "x": 0,
        "y": 18,
        "z": 1,
        "color": "#f4cbbe"
    },
    {
        "x": 0,
        "y": 18,
        "z": 2,
        "color": "#1b4aaa"
    },
    {
        "x": 1,
        "y": 18,
        "z": -1,
        "color": "#1d4eb3"
    },
    {
        "x": 1,
        "y": 18,
        "z": 0,
        "color": "#f6d4ca"
    },
    {
        "x": 1,
        "y": 18,
        "z": 1,
        "color": "#f5cec3"
    },
    {
        "x": 1,
        "y": 18,
        "z": 2,
        "color": "#1e51b9"
    },
    {
        "x": 2,
        "y": 18,
        "z": -1,
        "color": "#2053bf"
    },
    {
        "x": 2,
        "y": 18,
        "z": 0,
        "color": "#f4cabe"
    },
    {
        "x": 2,
        "y": 18,
        "z": 1,
        "color": "#f6d7ce"
    },
    {
        "x": 2,
        "y": 18,
        "z": 2,
        "color": "#1c4bae"
    },
    {
        "x": 3,
        "y": 18,
        "z": 0,
        "color": "#1f52bd"
    },
    {
        "x": -2,
        "y": 19,
        "z": -1,
        "color": "#2054c1"
    },
    {
        "x": -2,
        "y": 19,
        "z": 0,
        "color": "#1e50b8"
    },
    {
        "x": -2,
        "y": 19,
        "z": 1,
        "color": "#f6d4ca"
    },
    {
        "x": -2,
        "y": 19,
        "z": 2,
        "color": "#1e4fb7"
    },
    {
        "x": -1,
        "y": 19,
        "z": -1,
        "color": "#1c4bad"
    },
    {
        "x": -1,
        "y": 19,
        "z": 0,
        "color": "#f6d5cb"
    },
    {
        "x": -1,
        "y": 19,
        "z": 1,
        "color": "#f4cabd"
    },
    {
        "x": -1,
        "y": 19,
        "z": 2,
        "color": "#2156c4"
    },
    {
        "x": 0,
        "y": 19,
        "z": -1,
        "color": "#1e4fb6"
    },
    {
        "x": 0,
        "y": 19,
        "z": 0,
        "color": "#f6d4ca"
    },
    {
        "x": 0,
        "y": 19,
        "z": 1,
        "color": "#f5d1c6"
    },
    {
        "x": 0,
        "y": 19,
        "z": 2,
        "color": "#1f52bd"
    },
    {
        "x": 1,
        "y": 19,
        "z": -1,
        "color": "#2054c0"
    },
    {
        "x": 1,
        "y": 19,
        "z": 0,
        "color": "#f4cbbf"
    },
    {
        "x": 1,
        "y": 19,
        "z": 1,
        "color": "#f6d6cc"
    },
    {
        "x": 1,
        "y": 19,
        "z": 2,
        "color": "#1c4cb0"
    },
    {
        "x": 2,
        "y": 19,
        "z": -1,
        "color": "#2156c4"
    },
    {
        "x": 2,
        "y": 19,
        "z": 0,
        "color": "#1e4fb6"
    },
    {
        "x": 2,
        "y": 19,
        "z": 1,
        "color": "#f6d6cd"
    },
    {
        "x": 2,
        "y": 19,
        "z": 2,
        "color": "#2055c2"
    },
    {
        "x": -2,
        "y": 20,
        "z": 0,
        "color": "#1d4eb4"
    },
    {
        "x": -2,
        "y": 20,
        "z": 1,
        "color": "#1c4caf"
    },
    {
        "x": -1,
        "y": 20,
        "z": -1,
        "color": "#1d4eb4"
    },
    {
        "x": -1,
        "y": 20,
        "z": 0,
        "color": "#2053bf"
    },
    {
        "x": -1,
        "y": 20,
        "z": 1,
        "color": "#1e4fb6"
    },
    {
        "x": 0,
        "y": 20,
        "z": -1,
        "color": "#2054bf"
    },
    {
        "x": 0,
        "y": 20,
        "z": 0,
        "color": "#1e50b8"
    },
    {
        "x": 0,
        "y": 20,
        "z": 1,
        "color": "#2054c1"
    },
    {
        "x": 1,
        "y": 20,
        "z": -1,
        "color": "#1f51bb"
    },
    {
        "x": 1,
        "y": 20,
        "z": 0,
        "color": "#2054c1"
    },
    {
        "x": 1,
        "y": 20,
        "z": 1,
        "color": "#1f52bc"
    },
    {
        "x": 2,
        "y": 20,
        "z": 0,
        "color": "#1b49aa"
    },
    {
        "x": 2,
        "y": 20,
        "z": 1,
        "color": "#2053bf"
    },
    {
        "x": -1,
        "y": 21,
        "z": 0,
        "color": "#2055c2"
    },
    {
        "x": -1,
        "y": 21,
        "z": 1,
        "color": "#2155c3"
    },
    {
        "x": 0,
        "y": 21,
        "z": 0,
        "color": "#1d4fb5"
    },
    {
        "x": 0,
        "y": 21,
        "z": 1,
        "color": "#2054c1"
    },
    {
        "x": 1,
        "y": 21,
        "z": 0,
        "color": "#1f52bd"
    },
    {
        "x": 1,
        "y": 21,
        "z": 1,
        "color": "#1e51ba"
    },
    {
        "x": -3,
        "y": 17,
        "z": -1,
        "color": "#2156c4"
    },
    {
        "x": -4,
        "y": 16,
        "z": -1,
        "color": "#1f53be"
    },
    {
        "x": 3,
        "y": 17,
        "z": -1,
        "color": "#2054c1"
    },
    {
        "x": 4,
        "y": 16,
        "z": -1,
        "color": "#1f53bd"
    },
    {
        "x": 0,
        "y": 20,
        "z": -2,
        "color": "#2054c1"
    },
    {
        "x": 0,
        "y": 19,
        "z": -3,
        "color": "#2156c4"
    },
    {
        "x": 0,
        "y": 18,
        "z": -4,
        "color": "#1f52bc"
    },
    {
        "x": 0,
        "y": 17,
        "z": -5,
        "color": "#2054c0"
    },
    {
        "x": -1,
        "y": 19,
        "z": -2,
        "color": "#2053bf"
    },
    {
        "x": -1,
        "y": 18,
        "z": -3,
        "color": "#2053bf"
    },
    {
        "x": -1,
        "y": 17,
        "z": -4,
        "color": "#1c4cb0"
    },
    {
        "x": -1,
        "y": 16,
        "z": -5,
        "color": "#1d4eb4"
    },
    {
        "x": 1,
        "y": 19,
        "z": -2,
        "color": "#2054c1"
    },
    {
        "x": 1,
        "y": 18,
        "z": -3,
        "color": "#1c4bae"
    },
    {
        "x": 1,
        "y": 17,
        "z": -4,
        "color": "#1d4eb4"
    },
    {
        "x": 1,
        "y": 16,
        "z": -5,
        "color": "#1d4fb5"
    },
    {
        "x": -2,
        "y": 17,
        "z": -2,
        "color": "#2054c1"
    },
    {
        "x": -2,
        "y": 16,
        "z": -3,
        "color": "#1b4aac"
    },
    {
        "x": -2,
        "y": 15,
        "z": -4,
        "color": "#2055c2"
    },
    {
        "x": -2,
        "y": 14,
        "z": -5,
        "color": "#1c4bad"
    },
    {
        "x": 2,
        "y": 17,
        "z": -2,
        "color": "#1b49aa"
    },
    {
        "x": 2,
        "y": 16,
        "z": -3,
        "color": "#2155c3"
    },
    {
        "x": 2,
        "y": 15,
        "z": -4,
        "color": "#1d4fb6"
    },
    {
        "x": 2,
        "y": 14,
        "z": -5,
        "color": "#1f52bc"
    },
    {
        "x": -1,
        "y": 15,
        "z": -2,
        "color": "#1d4eb4"
    },
    {
        "x": -1,
        "y": 14,
        "z": -3,
        "color": "#1e50b8"
    },
    {
        "x": -1,
        "y": 13,
        "z": -4,
        "color": "#1d4eb5"
    },
    {
        "x": 1,
        "y": 15,
        "z": -2,
        "color": "#2156c5"
    },
    {
        "x": 1,
        "y": 14,
        "z": -3,
        "color": "#1d4fb6"
    },
    {
        "x": 1,
        "y": 13,
        "z": -4,
        "color": "#1c4bad"
    },
    {
        "x": 0,
        "y": 17,
        "z": 4,
        "color": "#1c4caf"
    },
    {
        "x": 0,
        "y": 16,
        "z": 5,
        "color": "#1e4fb7"
    }
]